LICENSE
MANIFEST.in
README.md
requirements.txt
setup.cfg
setup.py
django_mp_flatpages.egg-info/PKG-INFO
django_mp_flatpages.egg-info/SOURCES.txt
django_mp_flatpages.egg-info/dependency_links.txt
django_mp_flatpages.egg-info/top_level.txt
flatpages/__init__.py
flatpages/admin.py
flatpages/forms.py
flatpages/models.py
flatpages/seo.py
flatpages/sitemap.py
flatpages/translation.py
flatpages/urls.py
flatpages/views.py
flatpages/locale/ru/LC_MESSAGES/django.mo
flatpages/locale/ru/LC_MESSAGES/django.po
flatpages/locale/uk/LC_MESSAGES/django.mo
flatpages/locale/uk/LC_MESSAGES/django.po
flatpages/migrations/0001_initial.py
flatpages/migrations/__init__.py
flatpages/templates/flatpages/default.html