Metadata-Version: 1.1
Name: django-mp-flatpages
Version: 4.1.2
Summary: Django flatpages app
Home-page: https://github.com/pmaigutyak/mp-flatpages
Author: Paul Maigutyak
Author-email: pmaigutyak@gmail.com
License: MIT
Download-URL: https://github.com/pmaigutyak/mp-flatpages/archive/4.1.2.tar.gz
Platform: UNKNOWN
